utubetomp/__init__.py
utubetomp/intro.txt
utubetomp/utubetomp.py
utubetomp-0.1.1.dist-info/WHEEL
utubetomp-0.1.1.dist-info/METADATA
utubetomp-0.1.1.dist-info/RECORD
